{
    "server": {
        "listen_addr" : "178.1.207.7:10000",
        "certificate" : "/home/justus/Documents/Code/quicheperf-stun/src/cert.crt",
        "key" : "/home/justus/Documents/Code/quicheperf-stun/src/cert.key",
        "flags" : "--mp true",
        "stun_url": "stun:stun.l.google.com:19302",
        "interfaces": [
            "eth0"
        ],
        "log_level": "info"
    },
    "client": {
        "listen_addr" : "192.168.2.10:20000",
        "duration" : 100,
        "bandwidth": "1MB",
        "flags" : "--mp true",
        "stun_url": "stun:stun.l.google.com:19302",
        "interfaces": [
            "wlp5s0",
            "enx00e04c19aee4"
        ],
        "log_level": "info"
    }
}
